{
    "Personagens": [
        {
          "Nome": "Goku",
          "descricao1": "(Goku (孫 悟空, Son Gokū, ou Son Goku), nascido Kakarotto (カカロット, Kakarotto) é o protagonista das franquias Dragon Ball. Ele é neto adotivo de Vovô Gohan, filho de Bardock e Gine, o irmão mais novo de Raditz, o marido de Chichi, pai de Gohan e Goten, avô de Pan e mais tarde tataravô de Goku Jr. Sua primeira aparição ocorreu em 1984, no primeiro capítulo do mangá Dragon Ball, publicado na revista Weekly Shōnen Jump. Goku é inspirado em Sun Wukong, personagem do romance Jornada ao Oeste. Porém, Toriyama mudou algumas de suas características para ser mais original. Goku é apresentado como um menino estranho com rabo de macaco e força sobre-humana. Alegre, corajoso, e também um pouco ingênuo, Goku é um Saiyajin originalmente enviado à Terra quando criança com a missão de destruí-la. Porém, um acidente altera sua memória, fazendo-o crescer com um coração puro e depois se torna o maior defensor da Terra, e também o líder informal dos Guerreiros Z. Através da sua vida, ele treina duro e deseja ser o melhor guerreiro possível, e ao mesmo tempo usando sua força incrível para manter a paz."
        },
       {
         "Nome": "Vegeta",
          "descricao2": "Vegeta (ベジータ Bejīta), mais especificamente Vegeta IV (ベジータ四世 Bejīta Yonsei), reconhecido como Príncipe Vegeta (ベジータ王子 Bejīta Ōji), é o príncipe da raça Saiyajin caída e marido de Bulma, pai de Trunks. e Bulla, o filho mais velho do Rei Vegeta, além de um dos personagens principais da série Dragon Ball. Majestoso, egoísta e cheio de orgulho, Vegeta já foi um guerreiro cruel e de sangue frio e um assassino absoluto, mas depois abandonou sua posição na Força Frieza para uma vida pacífica na Terra. Ele lutaria repetidamente ao lado dos guerreiros mais poderosos do Universo 7 para proteger a Terra e sua família, bem como para superar Goku no poder. O forte desenvolvimento do personagem de Vegeta recebeu muitos elogios e é considerado o maior da série. Ele inicialmente estreou como o principal antagonista da Saga Vegeta, mas progrediu para um papel tritagonista mais anti-heróico para o resto de Dragon Ball Z. Desde a Saga Majin Buu e entrando em Dragon Ball Super, Vegeta tem sido o principal deuteragonista/protagonista secundário. atrás de Goku."
        }
    ]
}
